sirepo/__init__.py
sirepo/agent_supervisor_api.py
sirepo/api_auth.py
sirepo/api_perm.py
sirepo/auth_api.py
sirepo/auth_role.py
sirepo/auth_role_moderation.py
sirepo/const.py
sirepo/cookie.py
sirepo/cron.py
sirepo/crystal.py
sirepo/csv.py
sirepo/db_upgrade.py
sirepo/events.py
sirepo/exporter.py
sirepo/feature_config.py
sirepo/file_lock.py
sirepo/html.py
sirepo/http_request.py
sirepo/http_util.py
sirepo/hundli_console.py
sirepo/importer.py
sirepo/job.py
sirepo/job_api.py
sirepo/job_supervisor.py
sirepo/jupyterhub.py
sirepo/lib.py
sirepo/modules.py
sirepo/mpi.py
sirepo/nersc.py
sirepo/numpy.py
sirepo/oauth.py
sirepo/payments.py
sirepo/quest.py
sirepo/reply.py
sirepo/request.py
sirepo/resource.py
sirepo/server.py
sirepo/sim_db_file.py
sirepo/sim_run.py
sirepo/simulation_db.py
sirepo/sirepo_console.py
sirepo/smtp.py
sirepo/spa_session.py
sirepo/srdb.py
sirepo/srschema.py
sirepo/srtime.py
sirepo/srunit.py
sirepo/srunit_api.py
sirepo/srunit_servers.py
sirepo/status.py
sirepo/tornado.py
sirepo/uri.py
sirepo/uri_router.py
sirepo/util.py
sirepo/analysis/__init__.py
sirepo/analysis/ml.py
sirepo/auth/__init__.py
sirepo/auth/basic.py
sirepo/auth/bluesky.py
sirepo/auth/email.py
sirepo/auth/guest.py
sirepo/auth/ldap.py
sirepo/auth_db/__init__.py
sirepo/auth_db/base.py
sirepo/auth_db/email.py
sirepo/auth_db/jupyterhub.py
sirepo/auth_db/stripe.py
sirepo/auth_db/user.py
sirepo/global_resources/__init__.py
sirepo/global_resources/api.py
sirepo/global_resources/myapp.py
sirepo/job_driver/__init__.py
sirepo/job_driver/docker.py
sirepo/job_driver/local.py
sirepo/job_driver/sbatch.py
sirepo/package_data/http-custom-error.html.jinja
sirepo/package_data/javascript-redirect.html.jinja
sirepo/package_data/jupyterhub_conf.py.jinja
sirepo/package_data/nginx_proxy.conf.jinja
sirepo/package_data/raydata-execute-analysis.sh.jinja
sirepo/package_data/auth_role_moderation/approve_email.jinja
sirepo/package_data/auth_role_moderation/clarify_email.jinja
sirepo-20260117.214835.dist-info/licenses/LICENSE
sirepo-20260117.214835.dist-info/METADATA
sirepo-20260117.214835.dist-info/WHEEL
sirepo-20260117.214835.dist-info/entry_points.txt
sirepo-20260117.214835.dist-info/top_level.txt
sirepo-20260117.214835.dist-info/RECORD
