Metadata-Version: 2.4
Name: sirepo
Version: 20260117.214835
Summary: Sirepo provides browser access to physics codes like elegant, Warp, SRW, JSPEC, Zgoubi, and more.
Author-email: RadiaSoft LLC <pip@radiasoft.net>
Project-URL: Homepage, https://sirepo.com
Classifier: Development Status :: 5 - Production/Stable
Classifier: Environment :: Console
Classifier: Environment :: Web Environment
Classifier: Intended Audience :: Developers
Classifier: Intended Audience :: Science/Research
Classifier: License :: OSI Approved :: Apache Software License
Classifier: Natural Language :: English
Classifier: Programming Language :: Python
Classifier: Topic :: Scientific/Engineering :: Physics
Classifier: Topic :: Software Development :: Libraries :: Application Frameworks
License-File: LICENSE
Requires-Dist: SQLAlchemy<2,>=1.4
Requires-Dist: aenum
Requires-Dist: aiofiles
Requires-Dist: aiohttp
Requires-Dist: asyncssh
Requires-Dist: cryptography>=2.8
Requires-Dist: matplotlib
Requires-Dist: msgpack
Requires-Dist: numconv
Requires-Dist: numpy
Requires-Dist: Pillow
Requires-Dist: pyIsEmail
Requires-Dist: pykern
Requires-Dist: pytest-asyncio
Requires-Dist: pytz
Requires-Dist: requests
Requires-Dist: stripe
Requires-Dist: tornado>=6.5.2
Requires-Dist: user-agents
Requires-Dist: websockets
Requires-Dist: Authlib>=0.13
Requires-Dist: dnspython
Requires-Dist: asyncssh
Requires-Dist: ldap3
Dynamic: license-file
